{
  "file_number": "260362",
  "detail_url": "https://sfgov.legistar.com/LegislationDetail.aspx?ID=7978143&GUID=2B33417B-E9D8-45F1-ADAC-8DC121060AE0&Options=&Search=",
  "name": "Planning Code - Balboa Reservoir Special Use District",
  "title": "Ordinance amending the Planning Code to make adjustments to the Balboa Reservoir Special Use District that allow for a connecting element between two buildings adjacent to South Street and across from the Brighton Paseo; establishing certain design parameters, authorizing residential and certain other uses, and adopting a maximum height at this location; affirming the Planning Commission’s determination under the California Environmental Quality Act; making findings of consistency with the General Plan, and the eight priority policies of Planning Code, Section 101.1; and adopting Planning Code, Section 302 findings of public necessity, convenience and general welfare related to the proposed amendments.",
  "type": "Ordinance",
  "status": "Mayors Office",
  "introduced": "4/7/2026",
  "on_agenda": null,
  "final_action": "6/16/2026",
  "enactment_date": null,
  "enactment_number": null,
  "in_control": "Land Use and Transportation Committee",
  "sponsors": [
    "Myrna Melgar",
    "Rafael Mandelman",
    "Chyanne Chen"
  ],
  "related_files": [
    "200423",
    "200422"
  ],
  "attachments": [
    {
      "name": "Leg Ver1",
      "url": "https://sfgov.legistar.com/View.ashx?M=F&ID=15380263&GUID=7C285855-045F-4E8C-BC32-C30FC1630430"
    },
    {
      "name": "Leg Dig Ver1",
      "url": "https://sfgov.legistar.com/View.ashx?M=F&ID=15380264&GUID=5432FA40-C063-4F00-858D-0214F836B9EE"
    },
    {
      "name": "Referral CEQA PC 041526",
      "url": "https://sfgov.legistar.com/View.ashx?M=F&ID=15390967&GUID=FB4A7DEB-0A96-4762-8553-4EEC9EE5B4FF"
    },
    {
      "name": "CEQA Findings 050726",
      "url": "https://sfgov.legistar.com/View.ashx?M=F&ID=15459147&GUID=475B0911-E935-4640-ADF4-AFD170EFA057"
    },
    {
      "name": "PC Transmittal 051926",
      "url": "https://sfgov.legistar.com/View.ashx?M=F&ID=15496737&GUID=E699A503-6A03-41F1-A435-38E44C83A4D0"
    },
    {
      "name": "Fig 249.90-1 Land Use Map",
      "url": "https://sfgov.legistar.com/View.ashx?M=F&ID=15497678&GUID=2CCF148C-F197-43F0-A5A5-1DDEF3F8D10E"
    },
    {
      "name": "Fig 249.90-2 Height Limit Map",
      "url": "https://sfgov.legistar.com/View.ashx?M=F&ID=15497679&GUID=D82A79A8-FCC6-44B4-BEE8-B804E2319FD7"
    },
    {
      "name": "Comm Pkt 060126",
      "url": "https://sfgov.legistar.com/View.ashx?M=F&ID=15512464&GUID=8155E04F-BFF7-4109-8646-EE46A954A39A"
    },
    {
      "name": "Board Pkt 060926",
      "url": "https://sfgov.legistar.com/View.ashx?M=F&ID=15560049&GUID=5D4B8EE6-8F0F-47C1-95D4-8471A9F48CDD"
    },
    {
      "name": "Board Pkt 061626",
      "url": "https://sfgov.legistar.com/View.ashx?M=F&ID=15580516&GUID=75F9A2C5-E9EC-42B6-84EE-53BA22F102EE"
    }
  ],
  "actions": [
    {
      "date": "6/16/2026",
      "body": "Board of Supervisors",
      "action": "FINALLY PASSED",
      "result": "Pass",
      "history_id": "36988865",
      "history_url": "https://sfgov.legistar.com/HistoryDetail.aspx?ID=36988865&GUID=5ADC2051-E142-4016-84E1-A33E084C800F",
      "votes": [
        {
          "person_id": "43525",
          "person_name": "Connie Chan",
          "vote_value": "Aye"
        },
        {
          "person_id": "312512",
          "person_name": "Chyanne Chen",
          "vote_value": "Aye"
        },
        {
          "person_id": "272292",
          "person_name": "Matt Dorsey",
          "vote_value": "Aye"
        },
        {
          "person_id": "312511",
          "person_name": "Jackie Fielder",
          "vote_value": "Excused"
        },
        {
          "person_id": "312510",
          "person_name": "Bilal Mahmood",
          "vote_value": "Aye"
        },
        {
          "person_id": "196476",
          "person_name": "Rafael Mandelman",
          "vote_value": "Aye"
        },
        {
          "person_id": "60155",
          "person_name": "Myrna Melgar",
          "vote_value": "Aye"
        },
        {
          "person_id": "312509",
          "person_name": "Danny Sauter",
          "vote_value": "Aye"
        },
        {
          "person_id": "312930",
          "person_name": "Stephen Sherrill",
          "vote_value": "Aye"
        },
        {
          "person_id": "160445",
          "person_name": "Shamann Walton",
          "vote_value": "Aye"
        },
        {
          "person_id": "330759",
          "person_name": "Alan Wong",
          "vote_value": "Aye"
        }
      ]
    },
    {
      "date": "6/9/2026",
      "body": "Board of Supervisors",
      "action": "PASSED ON FIRST READING",
      "result": "Pass",
      "history_id": "36936110",
      "history_url": "https://sfgov.legistar.com/HistoryDetail.aspx?ID=36936110&GUID=D548C362-B049-4AFA-8D37-41845C63118B",
      "votes": [
        {
          "person_id": "43525",
          "person_name": "Connie Chan",
          "vote_value": "Aye"
        },
        {
          "person_id": "312512",
          "person_name": "Chyanne Chen",
          "vote_value": "Aye"
        },
        {
          "person_id": "272292",
          "person_name": "Matt Dorsey",
          "vote_value": "Aye"
        },
        {
          "person_id": "312511",
          "person_name": "Jackie Fielder",
          "vote_value": "Excused"
        },
        {
          "person_id": "312510",
          "person_name": "Bilal Mahmood",
          "vote_value": "Aye"
        },
        {
          "person_id": "196476",
          "person_name": "Rafael Mandelman",
          "vote_value": "Aye"
        },
        {
          "person_id": "60155",
          "person_name": "Myrna Melgar",
          "vote_value": "Aye"
        },
        {
          "person_id": "312509",
          "person_name": "Danny Sauter",
          "vote_value": "Aye"
        },
        {
          "person_id": "312930",
          "person_name": "Stephen Sherrill",
          "vote_value": "Aye"
        },
        {
          "person_id": "160445",
          "person_name": "Shamann Walton",
          "vote_value": "Aye"
        },
        {
          "person_id": "330759",
          "person_name": "Alan Wong",
          "vote_value": "Aye"
        }
      ]
    },
    {
      "date": "6/1/2026",
      "body": "Land Use and Transportation Committee",
      "action": "RECOMMENDED",
      "result": "Pass",
      "history_id": "36840580",
      "history_url": "https://sfgov.legistar.com/HistoryDetail.aspx?ID=36840580&GUID=3F113F4F-743F-4561-B475-2D8682B5EAE0",
      "votes": [
        {
          "person_id": "60155",
          "person_name": "Myrna Melgar",
          "vote_value": "Aye"
        },
        {
          "person_id": "312512",
          "person_name": "Chyanne Chen",
          "vote_value": "Aye"
        },
        {
          "person_id": "312510",
          "person_name": "Bilal Mahmood",
          "vote_value": "Aye"
        }
      ]
    },
    {
      "date": "5/19/2026",
      "body": "Planning Commission",
      "action": "RESPONSE RECEIVED",
      "result": "",
      "history_id": "36822940",
      "history_url": "https://sfgov.legistar.com/HistoryDetail.aspx?ID=36822940&GUID=1C7EC6B9-5364-4938-A903-7DD1BFB9B7B1",
      "votes": []
    },
    {
      "date": "4/15/2026",
      "body": "Clerk of the Board",
      "action": "REFERRED TO DEPARTMENT",
      "result": "",
      "history_id": "36552946",
      "history_url": "https://sfgov.legistar.com/HistoryDetail.aspx?ID=36552946&GUID=DBBA3CFA-98FF-4095-AFCE-DEDBA073AC79",
      "votes": []
    },
    {
      "date": "4/7/2026",
      "body": "President",
      "action": "ASSIGNED UNDER 30 DAY RULE",
      "result": "",
      "history_id": "36519624",
      "history_url": "https://sfgov.legistar.com/HistoryDetail.aspx?ID=36519624&GUID=63E15FC0-9E63-4926-9DC8-478C81DAB76F",
      "votes": []
    }
  ],
  "full_text": null
}